textual_bee/__init__.py
textual_bee/app.css
textual_bee/word_list.json
textual_bee/words_utils.py
textual_bee-1.4.0.dist-info/entry_points.txt
textual_bee-1.4.0.dist-info/METADATA
textual_bee-1.4.0.dist-info/WHEEL
textual_bee-1.4.0.dist-info/RECORD
