Metadata-Version: 2.1
Name: textual-bee
Version: 1.4.0
Summary: A Spelling Bee game for your terminal!
Author: torshepherd
Author-email: tor.aksel.shepherd@gmail.com
Requires-Python: >=3.9,<4.0
Classifier: Programming Language :: Python :: 3
Classifier: Programming Language :: Python :: 3.9
Classifier: Programming Language :: Python :: 3.10
Classifier: Programming Language :: Python :: 3.11
Requires-Dist: click (>=8.1.3,<9.0.0)
Requires-Dist: textual (>=0.9.1,<0.10.0)
Requires-Dist: typing-extensions (>=4.0.0,<5.0.0) ; python_version < "3.10"
